statit_py/__init__.py
statit_py/utils.py
statit_py-0.0.8.dist-info/LICENSE
statit_py-0.0.8.dist-info/METADATA
statit_py-0.0.8.dist-info/WHEEL
statit_py-0.0.8.dist-info/top_level.txt
statit_py-0.0.8.dist-info/RECORD
