Metadata-Version: 2.1
Name: statit-py
Version: 0.0.8
Summary: Utilities for gostatit.com
Author-email: Azhar Gana <azhar.gana@yahoo.com>
Project-URL: Homepage, https://github.com/keyboardcat1/statit_py
Project-URL: Bug Tracker, https://github.com/keyboardcat1/statit_py/issues
Classifier: Programming Language :: Python :: 3
Classifier: License :: OSI Approved :: GNU General Public License v3 (GPLv3)
Classifier: Operating System :: OS Independent
Requires-Python: >=3.7
License-File: LICENSE
